setup.py
django_vega/__init__.py
django_vega/browser.py
django_vega/models.py
django_vega/render.py
django_vega/utils.py
django_vega/views.py
django_vega.egg-info/PKG-INFO
django_vega.egg-info/SOURCES.txt
django_vega.egg-info/dependency_links.txt
django_vega.egg-info/requires.txt
django_vega.egg-info/top_level.txt
django_vega/static/django_vega/vega-embed.js
django_vega/static/django_vega/vega-embed.min.js
django_vega/static/django_vega/vega-lite.js
django_vega/static/django_vega/vega-lite.min.js
django_vega/static/django_vega/vega.js
django_vega/static/django_vega/vega.min.js
django_vega/templates/django_vega/default.html